MANIFEST.in
README.txt
__init__.py
setup.py
./__init__.py
PyVRML97_accelerate.egg-info/PKG-INFO
PyVRML97_accelerate.egg-info/SOURCES.txt
PyVRML97_accelerate.egg-info/dependency_links.txt
PyVRML97_accelerate.egg-info/top_level.txt
src/fieldaccel2.c
src/fieldaccel2.pyx
src/frustcullaccel.c
src/frustcullaccel.pyx
src/tmatrixaccel.c
src/tmatrixaccel.pyx